modal_agents_sdk/__init__.py
modal_agents_sdk/_client.py
modal_agents_sdk/_constants.py
modal_agents_sdk/_errors.py
modal_agents_sdk/_host_hooks.py
modal_agents_sdk/_host_tools.py
modal_agents_sdk/_image.py
modal_agents_sdk/_options.py
modal_agents_sdk/_query.py
modal_agents_sdk/_sandbox.py
modal_agents_sdk/_types.py
modal_agents_sdk/_utils.py
modal_agents_sdk-0.1.5.dist-info/METADATA
modal_agents_sdk-0.1.5.dist-info/WHEEL
modal_agents_sdk-0.1.5.dist-info/licenses/LICENSE
modal_agents_sdk-0.1.5.dist-info/RECORD
