Metadata-Version: 2.4
Name: modal-agents-sdk
Version: 0.1.5
Summary: Run Claude Agent SDK agents in Modal sandboxes
Project-URL: Homepage, https://github.com/sshh12/modal-claude-agent-sdk-python
Project-URL: Documentation, https://github.com/sshh12/modal-claude-agent-sdk-python#readme
Project-URL: Repository, https://github.com/sshh12/modal-claude-agent-sdk-python
Project-URL: Issues, https://github.com/sshh12/modal-claude-agent-sdk-python/issues
Author-email: Shrivu Shankar <shrivu1122@gmail.com>
License-Expression: MIT
License-File: LICENSE
Keywords: agent,ai,anthropic,claude,modal,sandbox
Classifier: Development Status :: 3 - Alpha
Classifier: Intended Audience :: Developers
Classifier: License :: OSI Approved :: MIT License
Classifier: Programming Language :: Python :: 3
Classifier: Programming Language :: Python :: 3.10
Classifier: Programming Language :: Python :: 3.11
Classifier: Programming Language :: Python :: 3.12
Classifier: Topic :: Scientific/Engineering :: Artificial Intelligence
Requires-Python: >=3.10
Requires-Dist: anyio>=4.12.0
Requires-Dist: claude-agent-sdk>=0.1.20
Requires-Dist: modal>=1.3.0
Provides-Extra: dev
Requires-Dist: mypy>=1.14.0; extra == 'dev'
Requires-Dist: pre-commit>=4.0.0; extra == 'dev'
Requires-Dist: pytest-asyncio>=0.24.0; extra == 'dev'
Requires-Dist: pytest-cov>=6.0.0; extra == 'dev'
Requires-Dist: pytest>=8.0.0; extra == 'dev'
Requires-Dist: ruff>=0.9.0; extra == 'dev'
